easyticket_qrgen/__init__.py
easyticket_qrgen/qr_ticketgen.py
easyticket_qrgen-1.0.dist-info/LICENSE
easyticket_qrgen-1.0.dist-info/METADATA
easyticket_qrgen-1.0.dist-info/WHEEL
easyticket_qrgen-1.0.dist-info/top_level.txt
easyticket_qrgen-1.0.dist-info/RECORD
