Metadata-Version: 2.1
Name: easyticket-qrgen
Version: 1.0
Summary: Package for creating QR Codes for the event ticket system easy-ticket.
Home-page: https://github.com/FabianWe/easyticket_qrgen
Author: Fabian Wenzelmann
Author-email: fabianwen@posteo.eu
License: Apache License 2.0
Keywords: qr qr-code ticket event
Platform: UNKNOWN
Requires-Dist: Pillow (>=6.1)
Requires-Dist: pyqrcode (>=1.2.1)
